MANIFEST.in
README.rst
r10k-webhook.service
setup.cfg
setup.py
r10k_webhook.egg-info/PKG-INFO
r10k_webhook.egg-info/SOURCES.txt
r10k_webhook.egg-info/dependency_links.txt
r10k_webhook.egg-info/entry_points.txt
r10k_webhook.egg-info/requires.txt
r10k_webhook.egg-info/top_level.txt
r10kwebhook/__init__.py
r10kwebhook/hook.py
r10kwebhook/webserver.py