Metadata-Version: 1.1
Name: r10k-webhook
Version: 0.0.6
Summary: Wrapper for r10k
Home-page: https://github.com/dashcheulov/r10k-webhook
Author: Denis Ashcheulov
Author-email: UNKNOWN
License: GPL-3.0+
Keywords: r10k puppet webhook gitolite git
Platform: UNKNOWN
Classifier: Development Status :: 3 - Alpha
Classifier: Intended Audience :: System Administrators
Classifier: License :: OSI Approved :: GNU General Public License v3 or later (GPLv3+)
Classifier: Programming Language :: Python :: 3
Classifier: Programming Language :: Python :: 3.4
